[
    {
        "pk":1,
        "model":"catalogs.catalogitem",
        "fields":{
            "name":"first",
            "parent":null,
            "deleted":false,
            "slug":"first",
            "language_code":"en",
            "path":"first",
            "last_child":null,
            "icon":""
        }
    },
    {
        "pk":5,
        "model":"catalogs.catalogitem",
        "fields":{
            "name":"four",
            "parent":1,
            "deleted":false,
            "slug":"four",
            "language_code":"en",
            "path":"first/four",
            "last_child":null,
            "icon":""
        }
    },
    {
        "pk":6,
        "model":"catalogs.catalogitem",
        "fields":{
            "name":"six",
            "parent":5,
            "deleted":false,
            "slug":"six",
            "language_code":"en",
            "path":"first/four/six",
            "last_child":null,
            "icon":""
        }
    },
    {
        "pk":2,
        "model":"catalogs.catalogitem",
        "fields":{
            "name":"second",
            "parent":1,
            "deleted":false,
            "slug":"second",
            "language_code":"en",
            "path":"first/second",
            "last_child":null,
            "icon":""
        }
    },
    {
        "pk":4,
        "model":"catalogs.catalogitem",
        "fields":{
            "name":"five",
            "parent":2,
            "deleted":false,
            "slug":"five",
            "language_code":"en",
            "path":"first/second/five",
            "last_child":null,
            "icon":""
        }
    },
    {
        "pk":3,
        "model":"catalogs.catalogitem",
        "fields":{
            "name":"third",
            "parent":2,
            "deleted":false,
            "slug":"third",
            "language_code":"en",
            "path":"first/second/third",
            "last_child":null,
            "icon":""
        }
    },
    {
        "pk":7,
        "model":"catalogs.catalogitem",
        "fields":{
            "name":"seven",
            "parent":null,
            "deleted":false,
            "slug":"seven",
            "language_code":"en",
            "path":"seven",
            "last_child":null,
            "icon":""
        }
    }
]